tutorials/examples/example_2/src/full_adder.v
module full_adder (
    input wire a ,
    input wire b ,
    input wire cin ,
    output wire sum ,
    output wire cout
);

assign {cout , sum} = a + b + cin ;

endmodule

tutorials/examples/example_2/sim/tb_full_adder.v
`timescale 1ns/1ns

module tb_full_adder;

    // 1. ประกาศตัวแปร
    // input ของ Module ใช้ reg (เพราะเราต้องกำหนดค่าให้มัน)
    reg t_a;
    reg t_b;
    reg t_cin;
    
    // output ของ Module ใช้ wire (เพราะรับค่าจากการต่อสาย)
    wire t_sum;
    wire t_cout;

    // 2. เรียกใช้ (Instantiate) Module ที่เราจะเทส (Unit Under Test - UUT)
    full_adder uut (
        .a(t_a),
        .b(t_b),
        .cin(t_cin),
        .sum(t_sum),
        .cout(t_cout)
    );

    // 3. เริ่มการทดสอบ (Stimulus)
    initial begin
        // สร้างไฟล์สำหรับดู Waveform (GTKWave)
        $dumpfile("wave.vcd");
        $dumpvars(0, tb_full_adder);

        // แสดงผลทางหน้าจอ (Monitor changes)
        $monitor("Time: %0t | a = %b | b = %b | cin = %b | sum = %b | cout = %b", $time, t_a, t_b, t_cin , t_sum, t_cout);

        // ป้อนค่าทดสอบ (Truth Table)
        t_a = 0; t_b = 0; t_cin = 0; #10;
        t_a = 0; t_b = 0; t_cin = 1; #10;
        t_a = 0; t_b = 1; t_cin = 0; #10;
        t_a = 0; t_b = 1; t_cin = 1; #10;
        t_a = 1; t_b = 0; t_cin = 0; #10;
        t_a = 1; t_b = 0; t_cin = 1; #10;
        t_a = 1; t_b = 1; t_cin = 0; #10;
        t_a = 1; t_b = 1; t_cin = 1; #10;

        // จบการทำงาน
        $finish;
    end

endmodule

tutorials/examples/example_2/sim/wave.vcd
$date
	Wed Dec 10 11:01:40 2025
$end
$version
	Icarus Verilog
$end
$timescale
	1ns
$end
$scope module tb_full_adder $end
$var wire 1 ! t_sum $end
$var wire 1 " t_cout $end
$var reg 1 # t_a $end
$var reg 1 $ t_b $end
$var reg 1 % t_cin $end
$scope module uut $end
$var wire 1 # a $end
$var wire 1 $ b $end
$var wire 1 % cin $end
$var wire 1 ! sum $end
$var wire 1 " cout $end
$upscope $end
$upscope $end
$enddefinitions $end
$comment Show the parameter values. $end
$dumpall
$end
#0
$dumpvars
0%
0$
0#
0"
0!
$end
#10
1!
1%
#20
0%
1$
#30
0!
1"
1%
#40
0"
1!
0%
0$
1#
#50
0!
1"
1%
#60
0%
1$
#70
1!
1%
