labs/lab_1/src/seven_segment_decoder.v
module seven_segment_decoder (
    input  wire [3:0] data_in,
    output reg  [7:0] segments
);
    always @(*) begin
        case (data_in)
            4'b0000: segments = 8'b11000000; // 0
            4'b0001: segments = 8'b11111001; // 1
            4'b0010: segments = 8'b10100100; // 2
            4'b0011: segments = 8'b10110000; // 3
            4'b0100: segments = 8'b10011001; // 4
            4'b0101: segments = 8'b10010010; // 5
            4'b0110: segments = 8'b10000010; // 6
            4'b0111: segments = 8'b11111000; // 7
            4'b1000: segments = 8'b10000000; // 8
            4'b1001: segments = 8'b10010000; // 9
            4'b1010: segments = 8'b10001000; // A
            4'b1011: segments = 8'b10000011; // b
            4'b1100: segments = 8'b11000110; // C
            4'b1101: segments = 8'b10100001; // d
            4'b1110: segments = 8'b10000110; // E
            4'b1111: segments = 8'b10001110; // F
            default: segments = 8'b11111111; // Blank
        endcase
    end
    `ifdef COCOTB_SIM
        initial begin
            $dumpfile("wave.vcd");  // Name of the dump file
            $dumpvars(0, seven_segment_decoder);  // Dump all variables for the top module
        end
    `endif
endmodule

labs/lab_1/src/multiplexer.v
module multiplexer (
    input  wire [3:0] in_0 ,
    input  wire [3:0] in_1 ,
    input  wire selector,
    output wire [3:0] data_out
);

    assign data_out = selector ? in_1 : in_0;

endmodule

labs/lab_1/src/controller.v
module controller (
    input wire rst ,
    input wire clk ,
    output reg [3 : 0] an ,
    output reg selector
);

    reg [17 : 0] counter ;

    initial begin
        counter = 18'd0;
        an = 4'b1111;
        selector = 1'b0;
    end

    always @(posedge clk) begin
        
        if (rst) begin
            an <= 4'b1111;
            selector <= 1'b0;
            counter <= 18'd0;
        end else begin
            if (counter[17] == 0) begin
                an <= 4'b1110; // Activate the first digit (active low)
                selector <= 1'b0;
            end
            else begin
                an <= 4'b1101; // Activate the second digit (active low)
                selector <= 1'b1;
            end
            counter <= counter + 1;
        end

    end

endmodule

labs/lab_1/src/system.v
module system (
    input wire [7 : 0] sw ,
    input wire rst ,
    input wire clk ,
    output wire [3 : 0] an ,
    output wire [7 : 0] segments
);
    wire selector ;
    wire [3 : 0] data_out;

    controller controller_inst (
        .rst(rst),
        .clk(clk),
        .an(an),
        .selector(selector)
    );

    multiplexer multiplexer_inst (
        .in_0(sw[3:0]),
        .in_1(sw[7:4]),
        .selector(selector),
        .data_out(data_out)
    );

    seven_segment_decoder seven_segment_decoder_inst (
        .data_in(data_out),
        .segments(segments)
    );
    
endmodule

labs/lab_1/sim/sim_system/sim_system.v
`timescale 1ns / 1ps

module sim_system;

    // Signals
    reg [7:0] sw;
    reg rst, clk;
    wire [3:0] an;
    wire [7:0] segments;

    // Instantiate System
    system uut (
        .sw(sw),
        .rst(rst),
        .clk(clk),
        .an(an),
        .segments(segments)
    );

    // Clock Generation
    always #5 clk = ~clk;

    initial begin
        $dumpfile("wave_system.vcd");
        $dumpvars(0, sim_system);

        // Init
        clk = 0;
        rst = 1; // Reset active
        sw = 8'hC3; // 1100 0011 -> High=C (12), Low=3
        
        $display("Starting System Simulation...");
        #20;
        
        // Run
        rst = 0;
        $display("Reset Released. SW Input = %h", sw);
        
        // Check State 0 (Digit 3)
        #20;
        // uut.controller_inst.selector ควรเป็น 0
        // segments ควรเป็น pattern ของเลข 3 (0011) -> 10110000
        if (an === 4'b1110 && segments === 8'b10110000)
             $display("PASS: State 0 showing 3 (an=%b, seg=%b)", an, segments);
        else $error("FAIL: State 0 expected 3 (an=%b, seg=%b)", an, segments);

        // Force Counter
        $display("Forcing counter switch...");
        uut.controller_inst.counter = 18'd131070;
        
        #50;

        // Check State 1 (Digit C)
        // uut.controller_inst.selector ควรเป็น 1
        // segments ควรเป็น pattern ของเลข C (1100) -> 11000110
        if (an === 4'b1101 && segments === 8'b11000110)
             $display("PASS: State 1 showing C (an=%b, seg=%b)", an, segments);
        else $error("FAIL: State 1 expected C (an=%b, seg=%b)", an, segments);

        $finish;
    end

endmodule

labs/lab_1/sim/sim_system/wave_system.vcd
$date
	Sun Dec 21 03:49:48 2025
$end
$version
	Icarus Verilog
$end
$timescale
	1ps
$end
$scope module sim_system $end
$var wire 8 ! segments [7:0] $end
$var wire 4 " an [3:0] $end
$var reg 1 # clk $end
$var reg 1 $ rst $end
$var reg 8 % sw [7:0] $end
$scope module uut $end
$var wire 1 # clk $end
$var wire 1 $ rst $end
$var wire 8 & sw [7:0] $end
$var wire 1 ' selector $end
$var wire 8 ( segments [7:0] $end
$var wire 4 ) data_out [3:0] $end
$var wire 4 * an [3:0] $end
$scope module controller_inst $end
$var wire 1 # clk $end
$var wire 1 $ rst $end
$var reg 4 + an [3:0] $end
$var reg 18 , counter [17:0] $end
$var reg 1 ' selector $end
$upscope $end
$scope module multiplexer_inst $end
$var wire 4 - in_0 [3:0] $end
$var wire 4 . in_1 [3:0] $end
$var wire 1 ' selector $end
$var wire 4 / data_out [3:0] $end
$upscope $end
$scope module seven_segment_decoder_inst $end
$var wire 4 0 data_in [3:0] $end
$var reg 8 1 segments [7:0] $end
$upscope $end
$upscope $end
$upscope $end
$enddefinitions $end
$comment Show the parameter values. $end
$dumpall
$end
#0
$dumpvars
b10110000 1
b11 0
b11 /
b1100 .
b11 -
b0 ,
b1111 +
b1111 *
b11 )
b10110000 (
0'
b11000011 &
b11000011 %
1$
0#
b1111 "
b10110000 !
$end
#5000
1#
#10000
0#
#15000
1#
#20000
0#
0$
#25000
b1 ,
b1110 "
b1110 *
b1110 +
1#
#30000
0#
#35000
b10 ,
1#
#40000
0#
b11111111111111110 ,
#45000
b11111111111111111 ,
1#
#50000
0#
#55000
b100000000000000000 ,
1#
#60000
0#
#65000
b11000110 !
b11000110 (
b11000110 1
b1100 )
b1100 /
b1100 0
b100000000000000001 ,
1'
b1101 "
b1101 *
b1101 +
1#
#70000
0#
#75000
b100000000000000010 ,
1#
#80000
0#
#85000
b100000000000000011 ,
1#
