labs/lab_1/src/multiplexer.v
module multiplexer (
    input  wire [3:0] in_0 ,
    input  wire [3:0] in_1 ,
    input  wire selector,
    output wire [3:0] data_out
);

    assign data_out = selector ? in_1 : in_0;

endmodule

labs/lab_1/sim/sim_multiplexer/sim_multiplexer.v
`timescale 1ns / 1ps

module sim_multiplexer ();
  // reg/wire declaration
  reg  [3:0] in_0;
  reg  [3:0] in_1;
  reg        selector;
  wire [3:0] data_out;

  // instantiate the Multiplexer module
  multiplexer MultiplexerInst (
      .in_0(in_0),
      .in_1(in_1),
      .selector(selector),
      .data_out(data_out)
  );
  // instantiate variable
  integer flag = 0;
  integer TestCaseNo = 0;
  integer i;
  integer j;

  // task to check the output
  task check_output;
    input integer TestCaseNo;
    input reg [3:0] expected_data_out;  // Expected output
    begin
      if (data_out !== expected_data_out) begin
        $error(
            "ERROR: TestCaseNo %0d | Time = %0t | in_0 = %b, in_1 = %b, selector = %b | data_out = %b (Expected: %b)",
            TestCaseNo, $time, in_0, in_1, selector, data_out, expected_data_out);
        flag = 1;
      end
    end
  endtask

  // test cases
  initial begin
    $display("Starting Simulation...");
    $dumpfile("wave.vcd");
    // หมายเหตุ: ต้องเปลี่ยนชื่อ module ใน $dumpvars ให้ตรงกับชื่อ module ด้านบน
    $dumpvars(0, sim_multiplexer);
    for (i = 0; i < 16; i = i + 1) begin
      for (j = 0; j < 16; j = j + 1) begin
        in_0 = i;
        in_1 = j;
        selector = 0;
        #1;
        check_output(TestCaseNo, i);
        TestCaseNo = TestCaseNo + 1;
        selector   = 1;
        #1;
        check_output(TestCaseNo, j);
        TestCaseNo = TestCaseNo + 1;
      end
    end
    if (flag == 0) begin
      $display("All test cases pass");
    end else begin
      $display("Some test cases fail");
    end
    $finish;
  end

endmodule

labs/lab_1/sim/sim_multiplexer/wave.vcd
$date
	Mon Dec 15 03:36:27 2025
$end
$version
	Icarus Verilog
$end
$timescale
	1ps
$end
$scope module sim_multiplexer $end
$var wire 4 ! data_out [3:0] $end
$var reg 4 " in_0 [3:0] $end
$var reg 4 # in_1 [3:0] $end
$var reg 1 $ selector $end
$var integer 32 % TestCaseNo [31:0] $end
$var integer 32 & flag [31:0] $end
$var integer 32 ' i [31:0] $end
$var integer 32 ( j [31:0] $end
$scope module MultiplexerInst $end
$var wire 4 ) in_0 [3:0] $end
$var wire 4 * in_1 [3:0] $end
$var wire 1 $ selector $end
$var wire 4 + data_out [3:0] $end
$upscope $end
$scope task check_output $end
$var reg 4 , expected_data_out [3:0] $end
$var integer 32 - TestCaseNo [31:0] $end
$upscope $end
$upscope $end
$enddefinitions $end
$comment Show the parameter values. $end
$dumpall
$end
#0
$dumpvars
bx -
bx ,
b0 +
b0 *
b0 )
b0 (
b0 '
b0 &
b0 %
0$
b0 #
b0 "
b0 !
$end
#1000
1$
b1 %
b0 ,
b0 -
#2000
0$
b1 #
b1 *
b1 (
b10 %
b1 -
#3000
b1 !
b1 +
1$
b11 %
b10 -
#4000
b0 !
b0 +
0$
b10 #
b10 *
b10 (
b100 %
b1 ,
b11 -
#5000
b10 !
b10 +
1$
b101 %
b0 ,
b100 -
#6000
b0 !
b0 +
0$
b11 #
b11 *
b11 (
b110 %
b10 ,
b101 -
#7000
b11 !
b11 +
1$
b111 %
b0 ,
b110 -
#8000
b0 !
b0 +
0$
b100 #
b100 *
b100 (
b1000 %
b11 ,
b111 -
#9000
b100 !
b100 +
1$
b1001 %
b0 ,
b1000 -
#10000
b0 !
b0 +
0$
b101 #
b101 *
b101 (
b1010 %
b100 ,
b1001 -
#11000
b101 !
b101 +
1$
b1011 %
b0 ,
b1010 -
#12000
b0 !
b0 +
0$
b110 #
b110 *
b110 (
b1100 %
b101 ,
b1011 -
#13000
b110 !
b110 +
1$
b1101 %
b0 ,
b1100 -
#14000
b0 !
b0 +
0$
b111 #
b111 *
b111 (
b1110 %
b110 ,
b1101 -
#15000
b111 !
b111 +
1$
b1111 %
b0 ,
b1110 -
#16000
b0 !
b0 +
0$
b1000 #
b1000 *
b1000 (
b10000 %
b111 ,
b1111 -
#17000
b1000 !
b1000 +
1$
b10001 %
b0 ,
b10000 -
#18000
b0 !
b0 +
0$
b1001 #
b1001 *
b1001 (
b10010 %
b1000 ,
b10001 -
#19000
b1001 !
b1001 +
1$
b10011 %
b0 ,
b10010 -
#20000
b0 !
b0 +
0$
b1010 #
b1010 *
b1010 (
b10100 %
b1001 ,
b10011 -
#21000
b1010 !
b1010 +
1$
b10101 %
b0 ,
b10100 -
#22000
b0 !
b0 +
0$
b1011 #
b1011 *
b1011 (
b10110 %
b1010 ,
b10101 -
#23000
b1011 !
b1011 +
1$
b10111 %
b0 ,
b10110 -
#24000
b0 !
b0 +
0$
b1100 #
b1100 *
b1100 (
b11000 %
b1011 ,
b10111 -
#25000
b1100 !
b1100 +
1$
b11001 %
b0 ,
b11000 -
#26000
b0 !
b0 +
0$
b1101 #
b1101 *
b1101 (
b11010 %
b1100 ,
b11001 -
#27000
b1101 !
b1101 +
1$
b11011 %
b0 ,
b11010 -
#28000
b0 !
b0 +
0$
b1110 #
b1110 *
b1110 (
b11100 %
b1101 ,
b11011 -
#29000
b1110 !
b1110 +
1$
b11101 %
b0 ,
b11100 -
#30000
b0 !
b0 +
0$
b1111 #
b1111 *
b1111 (
b11110 %
b1110 ,
b11101 -
#31000
b1111 !
b1111 +
1$
b11111 %
b0 ,
b11110 -
#32000
b1 !
b1 +
0$
b0 #
b0 *
b1 "
b1 )
b1 '
b0 (
b100000 %
b1111 ,
b11111 -
#33000
b0 !
b0 +
1$
b100001 %
b1 ,
b100000 -
#34000
b1 !
b1 +
0$
b1 #
b1 *
b1 (
b100010 %
b0 ,
b100001 -
#35000
1$
b100011 %
b1 ,
b100010 -
#36000
0$
b10 #
b10 *
b10 (
b100100 %
b100011 -
#37000
b10 !
b10 +
1$
b100101 %
b100100 -
#38000
b1 !
b1 +
0$
b11 #
b11 *
b11 (
b100110 %
b10 ,
b100101 -
#39000
b11 !
b11 +
1$
b100111 %
b1 ,
b100110 -
#40000
b1 !
b1 +
0$
b100 #
b100 *
b100 (
b101000 %
b11 ,
b100111 -
#41000
b100 !
b100 +
1$
b101001 %
b1 ,
b101000 -
#42000
b1 !
b1 +
0$
b101 #
b101 *
b101 (
b101010 %
b100 ,
b101001 -
#43000
b101 !
b101 +
1$
b101011 %
b1 ,
b101010 -
#44000
b1 !
b1 +
0$
b110 #
b110 *
b110 (
b101100 %
b101 ,
b101011 -
#45000
b110 !
b110 +
1$
b101101 %
b1 ,
b101100 -
#46000
b1 !
b1 +
0$
b111 #
b111 *
b111 (
b101110 %
b110 ,
b101101 -
#47000
b111 !
b111 +
1$
b101111 %
b1 ,
b101110 -
#48000
b1 !
b1 +
0$
b1000 #
b1000 *
b1000 (
b110000 %
b111 ,
b101111 -
#49000
b1000 !
b1000 +
1$
b110001 %
b1 ,
b110000 -
#50000
b1 !
b1 +
0$
b1001 #
b1001 *
b1001 (
b110010 %
b1000 ,
b110001 -
#51000
b1001 !
b1001 +
1$
b110011 %
b1 ,
b110010 -
#52000
b1 !
b1 +
0$
b1010 #
b1010 *
b1010 (
b110100 %
b1001 ,
b110011 -
#53000
b1010 !
b1010 +
1$
b110101 %
b1 ,
b110100 -
#54000
b1 !
b1 +
0$
b1011 #
b1011 *
b1011 (
b110110 %
b1010 ,
b110101 -
#55000
b1011 !
b1011 +
1$
b110111 %
b1 ,
b110110 -
#56000
b1 !
b1 +
0$
b1100 #
b1100 *
b1100 (
b111000 %
b1011 ,
b110111 -
#57000
b1100 !
b1100 +
1$
b111001 %
b1 ,
b111000 -
#58000
b1 !
b1 +
0$
b1101 #
b1101 *
b1101 (
b111010 %
b1100 ,
b111001 -
#59000
b1101 !
b1101 +
1$
b111011 %
b1 ,
b111010 -
#60000
b1 !
b1 +
0$
b1110 #
b1110 *
b1110 (
b111100 %
b1101 ,
b111011 -
#61000
b1110 !
b1110 +
1$
b111101 %
b1 ,
b111100 -
#62000
b1 !
b1 +
0$
b1111 #
b1111 *
b1111 (
b111110 %
b1110 ,
b111101 -
#63000
b1111 !
b1111 +
1$
b111111 %
b1 ,
b111110 -
#64000
b10 !
b10 +
0$
b0 #
b0 *
b10 "
b10 )
b10 '
b0 (
b1000000 %
b1111 ,
b111111 -
#65000
b0 !
b0 +
1$
b1000001 %
b10 ,
b1000000 -
#66000
b10 !
b10 +
0$
b1 #
b1 *
b1 (
b1000010 %
b0 ,
b1000001 -
#67000
b1 !
b1 +
1$
b1000011 %
b10 ,
b1000010 -
#68000
b10 !
b10 +
0$
b10 #
b10 *
b10 (
b1000100 %
b1 ,
b1000011 -
#69000
1$
b1000101 %
b10 ,
b1000100 -
#70000
0$
b11 #
b11 *
b11 (
b1000110 %
b1000101 -
#71000
b11 !
b11 +
1$
b1000111 %
b1000110 -
#72000
b10 !
b10 +
0$
b100 #
b100 *
b100 (
b1001000 %
b11 ,
b1000111 -
#73000
b100 !
b100 +
1$
b1001001 %
b10 ,
b1001000 -
#74000
b10 !
b10 +
0$
b101 #
b101 *
b101 (
b1001010 %
b100 ,
b1001001 -
#75000
b101 !
b101 +
1$
b1001011 %
b10 ,
b1001010 -
#76000
b10 !
b10 +
0$
b110 #
b110 *
b110 (
b1001100 %
b101 ,
b1001011 -
#77000
b110 !
b110 +
1$
b1001101 %
b10 ,
b1001100 -
#78000
b10 !
b10 +
0$
b111 #
b111 *
b111 (
b1001110 %
b110 ,
b1001101 -
#79000
b111 !
b111 +
1$
b1001111 %
b10 ,
b1001110 -
#80000
b10 !
b10 +
0$
b1000 #
b1000 *
b1000 (
b1010000 %
b111 ,
b1001111 -
#81000
b1000 !
b1000 +
1$
b1010001 %
b10 ,
b1010000 -
#82000
b10 !
b10 +
0$
b1001 #
b1001 *
b1001 (
b1010010 %
b1000 ,
b1010001 -
#83000
b1001 !
b1001 +
1$
b1010011 %
b10 ,
b1010010 -
#84000
b10 !
b10 +
0$
b1010 #
b1010 *
b1010 (
b1010100 %
b1001 ,
b1010011 -
#85000
b1010 !
b1010 +
1$
b1010101 %
b10 ,
b1010100 -
#86000
b10 !
b10 +
0$
b1011 #
b1011 *
b1011 (
b1010110 %
b1010 ,
b1010101 -
#87000
b1011 !
b1011 +
1$
b1010111 %
b10 ,
b1010110 -
#88000
b10 !
b10 +
0$
b1100 #
b1100 *
b1100 (
b1011000 %
b1011 ,
b1010111 -
#89000
b1100 !
b1100 +
1$
b1011001 %
b10 ,
b1011000 -
#90000
b10 !
b10 +
0$
b1101 #
b1101 *
b1101 (
b1011010 %
b1100 ,
b1011001 -
#91000
b1101 !
b1101 +
1$
b1011011 %
b10 ,
b1011010 -
#92000
b10 !
b10 +
0$
b1110 #
b1110 *
b1110 (
b1011100 %
b1101 ,
b1011011 -
#93000
b1110 !
b1110 +
1$
b1011101 %
b10 ,
b1011100 -
#94000
b10 !
b10 +
0$
b1111 #
b1111 *
b1111 (
b1011110 %
b1110 ,
b1011101 -
#95000
b1111 !
b1111 +
1$
b1011111 %
b10 ,
b1011110 -
#96000
b11 !
b11 +
0$
b0 #
b0 *
b11 "
b11 )
b11 '
b0 (
b1100000 %
b1111 ,
b1011111 -
#97000
b0 !
b0 +
1$
b1100001 %
b11 ,
b1100000 -
#98000
b11 !
b11 +
0$
b1 #
b1 *
b1 (
b1100010 %
b0 ,
b1100001 -
#99000
b1 !
b1 +
1$
b1100011 %
b11 ,
b1100010 -
#100000
b11 !
b11 +
0$
b10 #
b10 *
b10 (
b1100100 %
b1 ,
b1100011 -
#101000
b10 !
b10 +
1$
b1100101 %
b11 ,
b1100100 -
#102000
b11 !
b11 +
0$
b11 #
b11 *
b11 (
b1100110 %
b10 ,
b1100101 -
#103000
1$
b1100111 %
b11 ,
b1100110 -
#104000
0$
b100 #
b100 *
b100 (
b1101000 %
b1100111 -
#105000
b100 !
b100 +
1$
b1101001 %
b1101000 -
#106000
b11 !
b11 +
0$
b101 #
b101 *
b101 (
b1101010 %
b100 ,
b1101001 -
#107000
b101 !
b101 +
1$
b1101011 %
b11 ,
b1101010 -
#108000
b11 !
b11 +
0$
b110 #
b110 *
b110 (
b1101100 %
b101 ,
b1101011 -
#109000
b110 !
b110 +
1$
b1101101 %
b11 ,
b1101100 -
#110000
b11 !
b11 +
0$
b111 #
b111 *
b111 (
b1101110 %
b110 ,
b1101101 -
#111000
b111 !
b111 +
1$
b1101111 %
b11 ,
b1101110 -
#112000
b11 !
b11 +
0$
b1000 #
b1000 *
b1000 (
b1110000 %
b111 ,
b1101111 -
#113000
b1000 !
b1000 +
1$
b1110001 %
b11 ,
b1110000 -
#114000
b11 !
b11 +
0$
b1001 #
b1001 *
b1001 (
b1110010 %
b1000 ,
b1110001 -
#115000
b1001 !
b1001 +
1$
b1110011 %
b11 ,
b1110010 -
#116000
b11 !
b11 +
0$
b1010 #
b1010 *
b1010 (
b1110100 %
b1001 ,
b1110011 -
#117000
b1010 !
b1010 +
1$
b1110101 %
b11 ,
b1110100 -
#118000
b11 !
b11 +
0$
b1011 #
b1011 *
b1011 (
b1110110 %
b1010 ,
b1110101 -
#119000
b1011 !
b1011 +
1$
b1110111 %
b11 ,
b1110110 -
#120000
b11 !
b11 +
0$
b1100 #
b1100 *
b1100 (
b1111000 %
b1011 ,
b1110111 -
#121000
b1100 !
b1100 +
1$
b1111001 %
b11 ,
b1111000 -
#122000
b11 !
b11 +
0$
b1101 #
b1101 *
b1101 (
b1111010 %
b1100 ,
b1111001 -
#123000
b1101 !
b1101 +
1$
b1111011 %
b11 ,
b1111010 -
#124000
b11 !
b11 +
0$
b1110 #
b1110 *
b1110 (
b1111100 %
b1101 ,
b1111011 -
#125000
b1110 !
b1110 +
1$
b1111101 %
b11 ,
b1111100 -
#126000
b11 !
b11 +
0$
b1111 #
b1111 *
b1111 (
b1111110 %
b1110 ,
b1111101 -
#127000
b1111 !
b1111 +
1$
b1111111 %
b11 ,
b1111110 -
#128000
b100 !
b100 +
0$
b0 #
b0 *
b100 "
b100 )
b100 '
b0 (
b10000000 %
b1111 ,
b1111111 -
#129000
b0 !
b0 +
1$
b10000001 %
b100 ,
b10000000 -
#130000
b100 !
b100 +
0$
b1 #
b1 *
b1 (
b10000010 %
b0 ,
b10000001 -
#131000
b1 !
b1 +
1$
b10000011 %
b100 ,
b10000010 -
#132000
b100 !
b100 +
0$
b10 #
b10 *
b10 (
b10000100 %
b1 ,
b10000011 -
#133000
b10 !
b10 +
1$
b10000101 %
b100 ,
b10000100 -
#134000
b100 !
b100 +
0$
b11 #
b11 *
b11 (
b10000110 %
b10 ,
b10000101 -
#135000
b11 !
b11 +
1$
b10000111 %
b100 ,
b10000110 -
#136000
b100 !
b100 +
0$
b100 #
b100 *
b100 (
b10001000 %
b11 ,
b10000111 -
#137000
1$
b10001001 %
b100 ,
b10001000 -
#138000
0$
b101 #
b101 *
b101 (
b10001010 %
b10001001 -
#139000
b101 !
b101 +
1$
b10001011 %
b10001010 -
#140000
b100 !
b100 +
0$
b110 #
b110 *
b110 (
b10001100 %
b101 ,
b10001011 -
#141000
b110 !
b110 +
1$
b10001101 %
b100 ,
b10001100 -
#142000
b100 !
b100 +
0$
b111 #
b111 *
b111 (
b10001110 %
b110 ,
b10001101 -
#143000
b111 !
b111 +
1$
b10001111 %
b100 ,
b10001110 -
#144000
b100 !
b100 +
0$
b1000 #
b1000 *
b1000 (
b10010000 %
b111 ,
b10001111 -
#145000
b1000 !
b1000 +
1$
b10010001 %
b100 ,
b10010000 -
#146000
b100 !
b100 +
0$
b1001 #
b1001 *
b1001 (
b10010010 %
b1000 ,
b10010001 -
#147000
b1001 !
b1001 +
1$
b10010011 %
b100 ,
b10010010 -
#148000
b100 !
b100 +
0$
b1010 #
b1010 *
b1010 (
b10010100 %
b1001 ,
b10010011 -
#149000
b1010 !
b1010 +
1$
b10010101 %
b100 ,
b10010100 -
#150000
b100 !
b100 +
0$
b1011 #
b1011 *
b1011 (
b10010110 %
b1010 ,
b10010101 -
#151000
b1011 !
b1011 +
1$
b10010111 %
b100 ,
b10010110 -
#152000
b100 !
b100 +
0$
b1100 #
b1100 *
b1100 (
b10011000 %
b1011 ,
b10010111 -
#153000
b1100 !
b1100 +
1$
b10011001 %
b100 ,
b10011000 -
#154000
b100 !
b100 +
0$
b1101 #
b1101 *
b1101 (
b10011010 %
b1100 ,
b10011001 -
#155000
b1101 !
b1101 +
1$
b10011011 %
b100 ,
b10011010 -
#156000
b100 !
b100 +
0$
b1110 #
b1110 *
b1110 (
b10011100 %
b1101 ,
b10011011 -
#157000
b1110 !
b1110 +
1$
b10011101 %
b100 ,
b10011100 -
#158000
b100 !
b100 +
0$
b1111 #
b1111 *
b1111 (
b10011110 %
b1110 ,
b10011101 -
#159000
b1111 !
b1111 +
1$
b10011111 %
b100 ,
b10011110 -
#160000
b101 !
b101 +
0$
b0 #
b0 *
b101 "
b101 )
b101 '
b0 (
b10100000 %
b1111 ,
b10011111 -
#161000
b0 !
b0 +
1$
b10100001 %
b101 ,
b10100000 -
#162000
b101 !
b101 +
0$
b1 #
b1 *
b1 (
b10100010 %
b0 ,
b10100001 -
#163000
b1 !
b1 +
1$
b10100011 %
b101 ,
b10100010 -
#164000
b101 !
b101 +
0$
b10 #
b10 *
b10 (
b10100100 %
b1 ,
b10100011 -
#165000
b10 !
b10 +
1$
b10100101 %
b101 ,
b10100100 -
#166000
b101 !
b101 +
0$
b11 #
b11 *
b11 (
b10100110 %
b10 ,
b10100101 -
#167000
b11 !
b11 +
1$
b10100111 %
b101 ,
b10100110 -
#168000
b101 !
b101 +
0$
b100 #
b100 *
b100 (
b10101000 %
b11 ,
b10100111 -
#169000
b100 !
b100 +
1$
b10101001 %
b101 ,
b10101000 -
#170000
b101 !
b101 +
0$
b101 #
b101 *
b101 (
b10101010 %
b100 ,
b10101001 -
#171000
1$
b10101011 %
b101 ,
b10101010 -
#172000
0$
b110 #
b110 *
b110 (
b10101100 %
b10101011 -
#173000
b110 !
b110 +
1$
b10101101 %
b10101100 -
#174000
b101 !
b101 +
0$
b111 #
b111 *
b111 (
b10101110 %
b110 ,
b10101101 -
#175000
b111 !
b111 +
1$
b10101111 %
b101 ,
b10101110 -
#176000
b101 !
b101 +
0$
b1000 #
b1000 *
b1000 (
b10110000 %
b111 ,
b10101111 -
#177000
b1000 !
b1000 +
1$
b10110001 %
b101 ,
b10110000 -
#178000
b101 !
b101 +
0$
b1001 #
b1001 *
b1001 (
b10110010 %
b1000 ,
b10110001 -
#179000
b1001 !
b1001 +
1$
b10110011 %
b101 ,
b10110010 -
#180000
b101 !
b101 +
0$
b1010 #
b1010 *
b1010 (
b10110100 %
b1001 ,
b10110011 -
#181000
b1010 !
b1010 +
1$
b10110101 %
b101 ,
b10110100 -
#182000
b101 !
b101 +
0$
b1011 #
b1011 *
b1011 (
b10110110 %
b1010 ,
b10110101 -
#183000
b1011 !
b1011 +
1$
b10110111 %
b101 ,
b10110110 -
#184000
b101 !
b101 +
0$
b1100 #
b1100 *
b1100 (
b10111000 %
b1011 ,
b10110111 -
#185000
b1100 !
b1100 +
1$
b10111001 %
b101 ,
b10111000 -
#186000
b101 !
b101 +
0$
b1101 #
b1101 *
b1101 (
b10111010 %
b1100 ,
b10111001 -
#187000
b1101 !
b1101 +
1$
b10111011 %
b101 ,
b10111010 -
#188000
b101 !
b101 +
0$
b1110 #
b1110 *
b1110 (
b10111100 %
b1101 ,
b10111011 -
#189000
b1110 !
b1110 +
1$
b10111101 %
b101 ,
b10111100 -
#190000
b101 !
b101 +
0$
b1111 #
b1111 *
b1111 (
b10111110 %
b1110 ,
b10111101 -
#191000
b1111 !
b1111 +
1$
b10111111 %
b101 ,
b10111110 -
#192000
b110 !
b110 +
0$
b0 #
b0 *
b110 "
b110 )
b110 '
b0 (
b11000000 %
b1111 ,
b10111111 -
#193000
b0 !
b0 +
1$
b11000001 %
b110 ,
b11000000 -
#194000
b110 !
b110 +
0$
b1 #
b1 *
b1 (
b11000010 %
b0 ,
b11000001 -
#195000
b1 !
b1 +
1$
b11000011 %
b110 ,
b11000010 -
#196000
b110 !
b110 +
0$
b10 #
b10 *
b10 (
b11000100 %
b1 ,
b11000011 -
#197000
b10 !
b10 +
1$
b11000101 %
b110 ,
b11000100 -
#198000
b110 !
b110 +
0$
b11 #
b11 *
b11 (
b11000110 %
b10 ,
b11000101 -
#199000
b11 !
b11 +
1$
b11000111 %
b110 ,
b11000110 -
#200000
b110 !
b110 +
0$
b100 #
b100 *
b100 (
b11001000 %
b11 ,
b11000111 -
#201000
b100 !
b100 +
1$
b11001001 %
b110 ,
b11001000 -
#202000
b110 !
b110 +
0$
b101 #
b101 *
b101 (
b11001010 %
b100 ,
b11001001 -
#203000
b101 !
b101 +
1$
b11001011 %
b110 ,
b11001010 -
#204000
b110 !
b110 +
0$
b110 #
b110 *
b110 (
b11001100 %
b101 ,
b11001011 -
#205000
1$
b11001101 %
b110 ,
b11001100 -
#206000
0$
b111 #
b111 *
b111 (
b11001110 %
b11001101 -
#207000
b111 !
b111 +
1$
b11001111 %
b11001110 -
#208000
b110 !
b110 +
0$
b1000 #
b1000 *
b1000 (
b11010000 %
b111 ,
b11001111 -
#209000
b1000 !
b1000 +
1$
b11010001 %
b110 ,
b11010000 -
#210000
b110 !
b110 +
0$
b1001 #
b1001 *
b1001 (
b11010010 %
b1000 ,
b11010001 -
#211000
b1001 !
b1001 +
1$
b11010011 %
b110 ,
b11010010 -
#212000
b110 !
b110 +
0$
b1010 #
b1010 *
b1010 (
b11010100 %
b1001 ,
b11010011 -
#213000
b1010 !
b1010 +
1$
b11010101 %
b110 ,
b11010100 -
#214000
b110 !
b110 +
0$
b1011 #
b1011 *
b1011 (
b11010110 %
b1010 ,
b11010101 -
#215000
b1011 !
b1011 +
1$
b11010111 %
b110 ,
b11010110 -
#216000
b110 !
b110 +
0$
b1100 #
b1100 *
b1100 (
b11011000 %
b1011 ,
b11010111 -
#217000
b1100 !
b1100 +
1$
b11011001 %
b110 ,
b11011000 -
#218000
b110 !
b110 +
0$
b1101 #
b1101 *
b1101 (
b11011010 %
b1100 ,
b11011001 -
#219000
b1101 !
b1101 +
1$
b11011011 %
b110 ,
b11011010 -
#220000
b110 !
b110 +
0$
b1110 #
b1110 *
b1110 (
b11011100 %
b1101 ,
b11011011 -
#221000
b1110 !
b1110 +
1$
b11011101 %
b110 ,
b11011100 -
#222000
b110 !
b110 +
0$
b1111 #
b1111 *
b1111 (
b11011110 %
b1110 ,
b11011101 -
#223000
b1111 !
b1111 +
1$
b11011111 %
b110 ,
b11011110 -
#224000
b111 !
b111 +
0$
b0 #
b0 *
b111 "
b111 )
b111 '
b0 (
b11100000 %
b1111 ,
b11011111 -
#225000
b0 !
b0 +
1$
b11100001 %
b111 ,
b11100000 -
#226000
b111 !
b111 +
0$
b1 #
b1 *
b1 (
b11100010 %
b0 ,
b11100001 -
#227000
b1 !
b1 +
1$
b11100011 %
b111 ,
b11100010 -
#228000
b111 !
b111 +
0$
b10 #
b10 *
b10 (
b11100100 %
b1 ,
b11100011 -
#229000
b10 !
b10 +
1$
b11100101 %
b111 ,
b11100100 -
#230000
b111 !
b111 +
0$
b11 #
b11 *
b11 (
b11100110 %
b10 ,
b11100101 -
#231000
b11 !
b11 +
1$
b11100111 %
b111 ,
b11100110 -
#232000
b111 !
b111 +
0$
b100 #
b100 *
b100 (
b11101000 %
b11 ,
b11100111 -
#233000
b100 !
b100 +
1$
b11101001 %
b111 ,
b11101000 -
#234000
b111 !
b111 +
0$
b101 #
b101 *
b101 (
b11101010 %
b100 ,
b11101001 -
#235000
b101 !
b101 +
1$
b11101011 %
b111 ,
b11101010 -
#236000
b111 !
b111 +
0$
b110 #
b110 *
b110 (
b11101100 %
b101 ,
b11101011 -
#237000
b110 !
b110 +
1$
b11101101 %
b111 ,
b11101100 -
#238000
b111 !
b111 +
0$
b111 #
b111 *
b111 (
b11101110 %
b110 ,
b11101101 -
#239000
1$
b11101111 %
b111 ,
b11101110 -
#240000
0$
b1000 #
b1000 *
b1000 (
b11110000 %
b11101111 -
#241000
b1000 !
b1000 +
1$
b11110001 %
b11110000 -
#242000
b111 !
b111 +
0$
b1001 #
b1001 *
b1001 (
b11110010 %
b1000 ,
b11110001 -
#243000
b1001 !
b1001 +
1$
b11110011 %
b111 ,
b11110010 -
#244000
b111 !
b111 +
0$
b1010 #
b1010 *
b1010 (
b11110100 %
b1001 ,
b11110011 -
#245000
b1010 !
b1010 +
1$
b11110101 %
b111 ,
b11110100 -
#246000
b111 !
b111 +
0$
b1011 #
b1011 *
b1011 (
b11110110 %
b1010 ,
b11110101 -
#247000
b1011 !
b1011 +
1$
b11110111 %
b111 ,
b11110110 -
#248000
b111 !
b111 +
0$
b1100 #
b1100 *
b1100 (
b11111000 %
b1011 ,
b11110111 -
#249000
b1100 !
b1100 +
1$
b11111001 %
b111 ,
b11111000 -
#250000
b111 !
b111 +
0$
b1101 #
b1101 *
b1101 (
b11111010 %
b1100 ,
b11111001 -
#251000
b1101 !
b1101 +
1$
b11111011 %
b111 ,
b11111010 -
#252000
b111 !
b111 +
0$
b1110 #
b1110 *
b1110 (
b11111100 %
b1101 ,
b11111011 -
#253000
b1110 !
b1110 +
1$
b11111101 %
b111 ,
b11111100 -
#254000
b111 !
b111 +
0$
b1111 #
b1111 *
b1111 (
b11111110 %
b1110 ,
b11111101 -
#255000
b1111 !
b1111 +
1$
b11111111 %
b111 ,
b11111110 -
#256000
b1000 !
b1000 +
0$
b0 #
b0 *
b1000 "
b1000 )
b1000 '
b0 (
b100000000 %
b1111 ,
b11111111 -
#257000
b0 !
b0 +
1$
b100000001 %
b1000 ,
b100000000 -
#258000
b1000 !
b1000 +
0$
b1 #
b1 *
b1 (
b100000010 %
b0 ,
b100000001 -
#259000
b1 !
b1 +
1$
b100000011 %
b1000 ,
b100000010 -
#260000
b1000 !
b1000 +
0$
b10 #
b10 *
b10 (
b100000100 %
b1 ,
b100000011 -
#261000
b10 !
b10 +
1$
b100000101 %
b1000 ,
b100000100 -
#262000
b1000 !
b1000 +
0$
b11 #
b11 *
b11 (
b100000110 %
b10 ,
b100000101 -
#263000
b11 !
b11 +
1$
b100000111 %
b1000 ,
b100000110 -
#264000
b1000 !
b1000 +
0$
b100 #
b100 *
b100 (
b100001000 %
b11 ,
b100000111 -
#265000
b100 !
b100 +
1$
b100001001 %
b1000 ,
b100001000 -
#266000
b1000 !
b1000 +
0$
b101 #
b101 *
b101 (
b100001010 %
b100 ,
b100001001 -
#267000
b101 !
b101 +
1$
b100001011 %
b1000 ,
b100001010 -
#268000
b1000 !
b1000 +
0$
b110 #
b110 *
b110 (
b100001100 %
b101 ,
b100001011 -
#269000
b110 !
b110 +
1$
b100001101 %
b1000 ,
b100001100 -
#270000
b1000 !
b1000 +
0$
b111 #
b111 *
b111 (
b100001110 %
b110 ,
b100001101 -
#271000
b111 !
b111 +
1$
b100001111 %
b1000 ,
b100001110 -
#272000
b1000 !
b1000 +
0$
b1000 #
b1000 *
b1000 (
b100010000 %
b111 ,
b100001111 -
#273000
1$
b100010001 %
b1000 ,
b100010000 -
#274000
0$
b1001 #
b1001 *
b1001 (
b100010010 %
b100010001 -
#275000
b1001 !
b1001 +
1$
b100010011 %
b100010010 -
#276000
b1000 !
b1000 +
0$
b1010 #
b1010 *
b1010 (
b100010100 %
b1001 ,
b100010011 -
#277000
b1010 !
b1010 +
1$
b100010101 %
b1000 ,
b100010100 -
#278000
b1000 !
b1000 +
0$
b1011 #
b1011 *
b1011 (
b100010110 %
b1010 ,
b100010101 -
#279000
b1011 !
b1011 +
1$
b100010111 %
b1000 ,
b100010110 -
#280000
b1000 !
b1000 +
0$
b1100 #
b1100 *
b1100 (
b100011000 %
b1011 ,
b100010111 -
#281000
b1100 !
b1100 +
1$
b100011001 %
b1000 ,
b100011000 -
#282000
b1000 !
b1000 +
0$
b1101 #
b1101 *
b1101 (
b100011010 %
b1100 ,
b100011001 -
#283000
b1101 !
b1101 +
1$
b100011011 %
b1000 ,
b100011010 -
#284000
b1000 !
b1000 +
0$
b1110 #
b1110 *
b1110 (
b100011100 %
b1101 ,
b100011011 -
#285000
b1110 !
b1110 +
1$
b100011101 %
b1000 ,
b100011100 -
#286000
b1000 !
b1000 +
0$
b1111 #
b1111 *
b1111 (
b100011110 %
b1110 ,
b100011101 -
#287000
b1111 !
b1111 +
1$
b100011111 %
b1000 ,
b100011110 -
#288000
b1001 !
b1001 +
0$
b0 #
b0 *
b1001 "
b1001 )
b1001 '
b0 (
b100100000 %
b1111 ,
b100011111 -
#289000
b0 !
b0 +
1$
b100100001 %
b1001 ,
b100100000 -
#290000
b1001 !
b1001 +
0$
b1 #
b1 *
b1 (
b100100010 %
b0 ,
b100100001 -
#291000
b1 !
b1 +
1$
b100100011 %
b1001 ,
b100100010 -
#292000
b1001 !
b1001 +
0$
b10 #
b10 *
b10 (
b100100100 %
b1 ,
b100100011 -
#293000
b10 !
b10 +
1$
b100100101 %
b1001 ,
b100100100 -
#294000
b1001 !
b1001 +
0$
b11 #
b11 *
b11 (
b100100110 %
b10 ,
b100100101 -
#295000
b11 !
b11 +
1$
b100100111 %
b1001 ,
b100100110 -
#296000
b1001 !
b1001 +
0$
b100 #
b100 *
b100 (
b100101000 %
b11 ,
b100100111 -
#297000
b100 !
b100 +
1$
b100101001 %
b1001 ,
b100101000 -
#298000
b1001 !
b1001 +
0$
b101 #
b101 *
b101 (
b100101010 %
b100 ,
b100101001 -
#299000
b101 !
b101 +
1$
b100101011 %
b1001 ,
b100101010 -
#300000
b1001 !
b1001 +
0$
b110 #
b110 *
b110 (
b100101100 %
b101 ,
b100101011 -
