labs/lab_1/src/seven_segment_decoder.v
module seven_segment_decoder (
    input  wire [3:0] data_in,
    output reg  [7:0] segments
);
    always @(*) begin
        case (data_in)
            4'b0000: segments = 8'b11000000; // 0
            4'b0001: segments = 8'b11111001; // 1
            4'b0010: segments = 8'b10100100; // 2
            4'b0011: segments = 8'b10110000; // 3
            4'b0100: segments = 8'b10011001; // 4
            4'b0101: segments = 8'b10010010; // 5
            4'b0110: segments = 8'b10000010; // 6
            4'b0111: segments = 8'b11111000; // 7
            4'b1000: segments = 8'b10000000; // 8
            4'b1001: segments = 8'b10010000; // 9
            4'b1010: segments = 8'b10001000; // A
            4'b1011: segments = 8'b10000011; // b
            4'b1100: segments = 8'b11000110; // C
            4'b1101: segments = 8'b10100001; // d
            4'b1110: segments = 8'b10000110; // E
            4'b1111: segments = 8'b10001110; // F
            default: segments = 8'b11111111; // Blank
        endcase
    end
    `ifdef COCOTB_SIM
        initial begin
            $dumpfile("wave.vcd");  // Name of the dump file
            $dumpvars(0, seven_segment_decoder);  // Dump all variables for the top module
        end
    `endif
endmodule

labs/lab_1/sim/sim_seven_segment_decoder/sim_seven_segment_decoder.v
`timescale 1ns / 1ps

module sim_seven_segment_decoder ();

  // 1. Declare signals (ใช้ชื่อแบบ Snake Case ตาม Module หลัก)
  reg  [3:0] data_in;
  wire [7:0] segments;

  // 2. Instantiate the Unit Under Test (UUT)
  seven_segment_decoder uut (
      .data_in (data_in),
      .segments(segments)
  );

  // Variable for tracking status
  integer flag = 0;

  // 3. Task to check the output
  task check_output;
    input [3:0] in_val;
    input [7:0] expected_val;
    begin
      data_in = in_val;
      #10; // รอเวลาให้สัญญาณเดินทาง (Propagation Delay)
      
      if (segments !== expected_val) begin
        $error("ERROR: Time=%0t | data_in=%h | segments=%b | Expected=%b", 
                $time, data_in, segments, expected_val);
        flag = 1;
      end
    end
  endtask

  // 4. Test Cases
  initial begin
    $display("Starting Simulation...");
    $dumpfile("wave.vcd");
    // หมายเหตุ: ต้องเปลี่ยนชื่อ module ใน $dumpvars ให้ตรงกับชื่อ module ด้านบน
    $dumpvars(0, sim_seven_segment_decoder);

    // ทดสอบค่า 0-9
    check_output(4'h0, 8'b11000000); // 0
    check_output(4'h1, 8'b11111001); // 1
    check_output(4'h2, 8'b10100100); // 2
    check_output(4'h3, 8'b10110000); // 3
    check_output(4'h4, 8'b10011001); // 4
    check_output(4'h5, 8'b10010010); // 5
    check_output(4'h6, 8'b10000010); // 6
    check_output(4'h7, 8'b11111000); // 7
    check_output(4'h8, 8'b10000000); // 8
    check_output(4'h9, 8'b10010000); // 9

    // ทดสอบค่า A-F
    check_output(4'hA, 8'b10001000); // A
    check_output(4'hB, 8'b10000011); // b
    check_output(4'hC, 8'b11000110); // C
    check_output(4'hD, 8'b10100001); // d
    check_output(4'hE, 8'b10000110); // E
    check_output(4'hF, 8'b10001110); // F

    // สรุปผล
    if (flag == 0) begin
      $display("----------------------------------");
      $display("    ALL TEST CASES PASSED       ");
      $display("----------------------------------");
    end else begin
      $display("----------------------------------");
      $display("    SOME TEST CASES FAILED      ");
      $display("----------------------------------");
    end

    $finish;
  end

endmodule

labs/lab_1/sim/sim_seven_segment_decoder/wave.vcd
$date
	Mon Dec 15 03:15:36 2025
$end
$version
	Icarus Verilog
$end
$timescale
	1ps
$end
$scope module sim_seven_segment_decoder $end
$var wire 8 ! segments [7:0] $end
$var reg 4 " data_in [3:0] $end
$var integer 32 # flag [31:0] $end
$scope module uut $end
$var wire 4 $ data_in [3:0] $end
$var reg 8 % segments [7:0] $end
$upscope $end
$scope task check_output $end
$var reg 8 & expected_val [7:0] $end
$var reg 4 ' in_val [3:0] $end
$upscope $end
$upscope $end
$enddefinitions $end
$comment Show the parameter values. $end
$dumpall
$end
#0
$dumpvars
b0 '
b11000000 &
b11000000 %
b0 $
b0 #
b0 "
b11000000 !
$end
#10000
b11111001 !
b11111001 %
b1 "
b1 $
b11111001 &
b1 '
#20000
b10100100 !
b10100100 %
b10 "
b10 $
b10100100 &
b10 '
#30000
b10110000 !
b10110000 %
b11 "
b11 $
b10110000 &
b11 '
#40000
b10011001 !
b10011001 %
b100 "
b100 $
b10011001 &
b100 '
#50000
b10010010 !
b10010010 %
b101 "
b101 $
b10010010 &
b101 '
#60000
b10000010 !
b10000010 %
b110 "
b110 $
b10000010 &
b110 '
#70000
b11111000 !
b11111000 %
b111 "
b111 $
b11111000 &
b111 '
#80000
b10000000 !
b10000000 %
b1000 "
b1000 $
b10000000 &
b1000 '
#90000
b10010000 !
b10010000 %
b1001 "
b1001 $
b10010000 &
b1001 '
#100000
b10001000 !
b10001000 %
b1010 "
b1010 $
b10001000 &
b1010 '
#110000
b10000011 !
b10000011 %
b1011 "
b1011 $
b10000011 &
b1011 '
#120000
b11000110 !
b11000110 %
b1100 "
b1100 $
b11000110 &
b1100 '
#130000
b10100001 !
b10100001 %
b1101 "
b1101 $
b10100001 &
b1101 '
#140000
b10000110 !
b10000110 %
b1110 "
b1110 $
b10000110 &
b1110 '
#150000
b10001110 !
b10001110 %
b1111 "
b1111 $
b10001110 &
b1111 '
