labs/lab_1/src/controller.v
module controller (
    input wire rst ,
    input wire clk ,
    output reg [3 : 0] an ,
    output reg selector
);

    reg [17 : 0] counter ;

    initial begin
        counter = 18'd0;
        an = 4'b1111;
        selector = 1'b0;
    end

    always @(posedge clk) begin
        
        if (rst) begin
            an <= 4'b1111;
            selector <= 1'b0;
            counter <= 18'd0;
        end else begin
            if (counter[17] == 0) begin
                an <= 4'b1110; // Activate the first digit (active low)
                selector <= 1'b0;
            end
            else begin
                an <= 4'b1101; // Activate the second digit (active low)
                selector <= 1'b1;
            end
            counter <= counter + 1;
        end

    end

endmodule

labs/lab_1/sim/sim_controller/sim_controller.v
`timescale 1ns / 1ps

module sim_controller;

    // 1. ประกาศตัวแปรสัญญาณ
    reg rst;
    reg clk;
    wire [3:0] an;
    wire selector;

    // 2. เรียกใช้ Module (UUT - Unit Under Test)
    controller uut (
        .rst(rst),
        .clk(clk),
        .an(an),
        .selector(selector)
    );

    // 3. สร้างสัญญาณนาฬิกา (Clock Generation)
    // คาบ 10ns (100MHz) -> Toggle ทุกๆ 5ns
    always #5 clk = ~clk;

    // 4. เริ่มต้นการทดสอบ
    initial begin
        // สร้างไฟล์สำหรับดู Waveform
        $dumpfile("wave.vcd");
        $dumpvars(0, sim_controller);

        // กำหนดค่าเริ่มต้น
        clk = 0;
        rst = 1; // กดปุ่ม Reset (Active High) ค้างไว้ตอนเริ่ม
        
        $display("Simulation Start...");

        // --- Phase 1: Reset Test ---
        #20; // รอ 20ns
        rst = 0; // ปล่อยปุ่ม Reset ให้วงจรทำงาน
        $display("Time: %0t | Reset Released", $time);

        // รอสักนิดเพื่อให้มั่นใจว่า logic เข้าสถานะแรกแล้ว
        #20;
        // ตรวจสอบสถานะแรก (ควรเป็น an=1110, selector=0)
        if (an === 4'b1110 && selector === 1'b0)
            $display("PASS: State 1 Correct (an=%b, selector=%b)", an, selector);
        else
            $error("FAIL: State 1 Incorrect (an=%b, selector=%b)", an, selector);


        // --- Phase 2: Transition Test (Hack Time) ---
        // ปกติต้องรอ 2^17 cycles (นับแสนรอบ) กว่าจะเปลี่ยนสถานะ
        // เราจะ "โกง" ด้วยการยัดค่าลงไปในตัวแปร counter ของ uut โดยตรง
        $display("Time: %0t | Forcing counter to near overflow...", $time);
        
        // เข้าถึงตัวแปรภายใน module uut.counter
        // ตั้งค่าไปที่ 131070 (อีก 2 clock จะถึงจุดเปลี่ยน 131072)
        uut.counter = 18'd131070; 

        #50; // ปล่อยเวลาวิ่งไปอีกนิดให้ counter นับข้ามขอบ

        // ตรวจสอบสถานะที่สอง (ควรเป็น an=1101, selector=1)
        if (an === 4'b1101 && selector === 1'b1)
            $display("PASS: State 2 Correct (an=%b, selector=%b)", an, selector);
        else
            $error("FAIL: State 2 Incorrect (an=%b, selector=%b)", an, selector);

        // จบการทำงาน
        $display("Simulation Finished");
        $finish;
    end

endmodule

labs/lab_1/sim/sim_controller/wave.vcd
$date
	Sun Dec 21 03:26:00 2025
$end
$version
	Icarus Verilog
$end
$timescale
	1ps
$end
$scope module sim_controller $end
$var wire 1 ! selector $end
$var wire 4 " an [3:0] $end
$var reg 1 # clk $end
$var reg 1 $ rst $end
$scope module uut $end
$var wire 1 # clk $end
$var wire 1 $ rst $end
$var reg 4 % an [3:0] $end
$var reg 18 & counter [17:0] $end
$var reg 1 ! selector $end
$upscope $end
$upscope $end
$enddefinitions $end
$comment Show the parameter values. $end
$dumpall
$end
#0
$dumpvars
b0 &
b1111 %
1$
0#
b1111 "
0!
$end
#5000
1#
#10000
0#
#15000
1#
#20000
0#
0$
#25000
b1 &
b1110 "
b1110 %
1#
#30000
0#
#35000
b10 &
1#
#40000
0#
b11111111111111110 &
#45000
b11111111111111111 &
1#
#50000
0#
#55000
b100000000000000000 &
1#
#60000
0#
#65000
b100000000000000001 &
1!
b1101 "
b1101 %
1#
#70000
0#
#75000
b100000000000000010 &
1#
#80000
0#
#85000
b100000000000000011 &
1#
